pycnt/__init__.py
pycnt/plotting.py
pycnt/pycnt.py
pycnt-0.1.0.dist-info/LICENSE
pycnt-0.1.0.dist-info/WHEEL
pycnt-0.1.0.dist-info/METADATA
pycnt-0.1.0.dist-info/RECORD
